{
  "$schema": "https://ui.shadcn.com/schema/registry-item.json",
  "name": "timeline-black-bruno",
  "title": "Timeline Black Bruno",
  "description": "Timeline Black Bruno template component",
  "registryDependencies": [],
  "files": [
    {
      "path": "registry/templates/timeline/timeline-black-bruno.tsx",
      "content": "import React from \"react\";\ntype TemplateProps = {\n  title?: string;\n  duration: string;\n  background?: string;\n  date?: string;\n  hours?: string;\n  text?: string;\n  tasks?: string[];\n  days?: string[];\n  dayDurations?: string[];\n  times?: string[];\n};\n\nexport const TimelineBlackBruno: React.FC<TemplateProps> = ({ title, times = [] }) => {\n  return (\n    <div className=\"relative w-full h-full overflow-hidden\">\n      <div className=\"flex flex-col justify-center items-center h-full p-6\">\n        <p className=\"text-2xl font-regular text-black font-bruno mb-2\">{title}</p>\n        <div className=\"w-20 h-8 border-t-2 border-l-2 border-r-2 border-black mb-0\"></div>\n        <div className=\"w-full h-0.5 bg-black mb-2\"></div>\n        <div className=\"flex justify-between items-center w-full\">\n          <p className=\"text-sm font-regular text-black font-inter\">{times[0]}</p>\n          <p className=\"text-sm font-regular text-black font-inter\">{times[1]}</p>\n          <p className=\"text-sm font-regular text-black font-inter\">{times[2]}</p>\n        </div>\n      </div>\n    </div>\n  );\n};\n\n",
      "type": "registry:component"
    }
  ],
  "type": "registry:component"
}